snirpinball/FONT.DAT
snirpinball/PINBALL.DAT
snirpinball/PINBALL.MID
snirpinball/PINBALL2.MID
snirpinball/SOUND1.WAV
snirpinball/SOUND104.WAV
snirpinball/SOUND105.WAV
snirpinball/SOUND108.WAV
snirpinball/SOUND111.WAV
snirpinball/SOUND112.WAV
snirpinball/SOUND12.WAV
snirpinball/SOUND13.WAV
snirpinball/SOUND131.WAV
snirpinball/SOUND136.WAV
snirpinball/SOUND14.WAV
snirpinball/SOUND16.WAV
snirpinball/SOUND17.WAV
snirpinball/SOUND18.WAV
snirpinball/SOUND181.WAV
snirpinball/SOUND19.WAV
snirpinball/SOUND20.WAV
snirpinball/SOUND21.WAV
snirpinball/SOUND22.WAV
snirpinball/SOUND24.WAV
snirpinball/SOUND240.WAV
snirpinball/SOUND243.WAV
snirpinball/SOUND25.WAV
snirpinball/SOUND26.WAV
snirpinball/SOUND27.WAV
snirpinball/SOUND28.WAV
snirpinball/SOUND29.WAV
snirpinball/SOUND3.WAV
snirpinball/SOUND30.WAV
snirpinball/SOUND34.WAV
snirpinball/SOUND35.WAV
snirpinball/SOUND36.WAV
snirpinball/SOUND38.WAV
snirpinball/SOUND39.WAV
snirpinball/SOUND4.WAV
snirpinball/SOUND42.WAV
snirpinball/SOUND43.WAV
snirpinball/SOUND45.WAV
snirpinball/SOUND49.WAV
snirpinball/SOUND49D.WAV
snirpinball/SOUND5.WAV
snirpinball/SOUND50.WAV
snirpinball/SOUND528.WAV
snirpinball/SOUND53.WAV
snirpinball/SOUND54.WAV
snirpinball/SOUND55.WAV
snirpinball/SOUND560.WAV
snirpinball/SOUND563.WAV
snirpinball/SOUND57.WAV
snirpinball/SOUND58.WAV
snirpinball/SOUND6.WAV
snirpinball/SOUND65.WAV
snirpinball/SOUND68.WAV
snirpinball/SOUND7.WAV
snirpinball/SOUND713.WAV
snirpinball/SOUND735.WAV
snirpinball/SOUND8.WAV
snirpinball/SOUND827.WAV
snirpinball/SOUND9.WAV
snirpinball/SOUND999.WAV
snirpinball/__init__.py
snirpinball/pinball.exe
snirpinball/table.bmp
snirpinball/wavemix.inf
snirpinball-0.2.0.dist-info/METADATA
snirpinball-0.2.0.dist-info/WHEEL
snirpinball-0.2.0.dist-info/top_level.txt
snirpinball-0.2.0.dist-info/RECORD
