Metadata-Version: 2.1
Name: snirpinball
Version: 0.2.0
Summary: a bot that can play pinball by himself
Home-page: UNKNOWN
Author: snir dekel
Author-email: snirdekel101@gmail.com
License: MIT
Keywords: computer vision
Platform: UNKNOWN
Classifier: Development Status :: 5 - Production/Stable
Classifier: Intended Audience :: Education
Classifier: Operating System :: Microsoft :: Windows :: Windows 10
Classifier: License :: OSI Approved :: MIT License
Classifier: Programming Language :: Python :: 3
Requires-Dist: mss
Requires-Dist: opencv-python
Requires-Dist: opencv-contrib-python
Requires-Dist: Pillow
Requires-Dist: pydirectinput
Requires-Dist: pyautogui
Requires-Dist: pygetwindow
